boltz2_client/__init__.py
boltz2_client/__main__.py
boltz2_client/a3m_to_csv_converter.py
boltz2_client/cli.py
boltz2_client/client.py
boltz2_client/exceptions.py
boltz2_client/models.py
boltz2_client/models_affinity.py
boltz2_client/msa_search.py
boltz2_client/multi_endpoint_client.py
boltz2_client/utils.py
boltz2_client/virtual_screening.py
boltz2_client/data/__init__.py
boltz2_client/data/speclist.txt
boltz2_python_client-0.3.3.dist-info/licenses/LICENSE
boltz2_python_client-0.3.3.dist-info/METADATA
boltz2_python_client-0.3.3.dist-info/WHEEL
boltz2_python_client-0.3.3.dist-info/entry_points.txt
boltz2_python_client-0.3.3.dist-info/top_level.txt
boltz2_python_client-0.3.3.dist-info/RECORD
