Metadata-Version: 2.4
Name: boltz2-python-client
Version: 0.3.3
Summary: Python client for Boltz-2 protein structure prediction API with covalent complex and multi-endpoint support
Author-email: NVIDIA Corporation <bionemo-support@nvidia.com>
Maintainer-email: NVIDIA Corporation <bionemo-support@nvidia.com>
License-Expression: MIT
Project-URL: Homepage, https://github.com/NVIDIA/digital-biology-examples/tree/main/examples/nims/boltz-2
Project-URL: Repository, https://github.com/NVIDIA/digital-biology-examples/tree/main/examples/nims/boltz-2
Project-URL: Documentation, https://github.com/NVIDIA/digital-biology-examples/tree/main/examples/nims/boltz-2/README.md
Project-URL: Bug Reports, https://github.com/NVIDIA/digital-biology-examples/issues
Keywords: protein,structure,prediction,AI,machine learning,bioinformatics,covalent,complex,boltz2
Classifier: Development Status :: 4 - Beta
Classifier: Intended Audience :: Science/Research
Classifier: Intended Audience :: Developers
Classifier: Operating System :: OS Independent
Classifier: Programming Language :: Python :: 3
Classifier: Programming Language :: Python :: 3.8
Classifier: Programming Language :: Python :: 3.9
Classifier: Programming Language :: Python :: 3.10
Classifier: Programming Language :: Python :: 3.11
Classifier: Programming Language :: Python :: 3.12
Classifier: Topic :: Scientific/Engineering :: Bio-Informatics
Classifier: Topic :: Scientific/Engineering :: Artificial Intelligence
Classifier: Topic :: Software Development :: Libraries :: Python Modules
Requires-Python: >=3.8
License-File: LICENSE
Requires-Dist: httpx>=0.24.0
Requires-Dist: pydantic>=2.0.0
Requires-Dist: typing-extensions>=4.0.0
Requires-Dist: aiofiles>=23.0.0
Requires-Dist: rich>=13.0.0
Requires-Dist: click>=8.0.0
Requires-Dist: PyYAML>=6.0.0
Requires-Dist: py3Dmol>=2.0.0
Dynamic: license-file
